pybabynames/__init__.py
pybabynames/data/applicants.parquet
pybabynames/data/babynames.parquet
pybabynames/data/births.parquet
pybabynames/data/lifetables.parquet
pybabynames-1.0.0.dist-info/METADATA
pybabynames-1.0.0.dist-info/WHEEL
pybabynames-1.0.0.dist-info/top_level.txt
pybabynames-1.0.0.dist-info/RECORD
