Metadata-Version: 2.1
Name: pybabynames
Version: 1.0.0
Summary: Python port of the R data package 'babynames'. This package provides US baby names data from the Social Security Administration (SSA). It contains all names used for at least 5 children of either sex in the United States. The package features the ability to switch between the data being imported as a Pandas DataFrame or a Polars DataFrame by setting an environment variable.
Author: James Joseph Balamuta
License: MIT
Project-URL: Homepage, https://github.com/coatless-py-pkg/pybabynames
Project-URL: Changelog, https://github.com/coatless-py-pkg/pybabynames/releases
Project-URL: Issues, https://github.com/coatless-py-pkg/pybabynames/issues
Project-URL: CI, https://github.com/coatless-py-pkg/pybabynames/actions
Classifier: Development Status :: 4 - Beta
Classifier: License :: OSI Approved :: MIT License
Classifier: Operating System :: OS Independent
Classifier: Programming Language :: Python :: 3
Requires-Python: >=3.9
Requires-Dist: pyarrow
Provides-Extra: docs
Requires-Dist: quartodoc ; extra == 'docs'
Requires-Dist: pandas ; extra == 'docs'
Requires-Dist: polars ; extra == 'docs'
Provides-Extra: pandas
Requires-Dist: pandas ; extra == 'pandas'
Provides-Extra: polars
Requires-Dist: polars ; extra == 'polars'
Provides-Extra: test
Requires-Dist: pytest ; extra == 'test'
Requires-Dist: pandas ; extra == 'test'
Requires-Dist: polars ; extra == 'test'
